Workbook

Sheet Instruções
A1: Tesouraria fictícia do TUNADÃO 1998
A2: Dados inventados, encadeados de janeiro de 2024 a setembro de 2026, usados para testar o gerador de relatórios. Nenhuma linha é real.

Sheet Listas
A1: Rubrica | B1: Tipo | C1: Conta como receita ou despesa | E1: Sub-rubrica | F1: Rubrica | H1: Atividade | J1: Meio | K1: Conta | M1: Orçamento
A2: Quotas | B2: Entrada | C2: Sim | E2: Apoio CMV | F2: Subsídios e apoios | H2: Funcionamento | J2: Caixa | K2: Caixa | M2: 20º CITADÃO
A3: Donativos | B3: Entrada | C3: Sim | E3: Apoio UPV (via AE ESAV) | F3: Subsídios e apoios | H3: Zumba na Caneca 2024 | J3: Banco | K3: Banco | M3: 2025
A4: Subsídios e apoios | B4: Entrada | C4: Sim | E4: Apoio Junta de Freguesia | F4: Subsídios e apoios | H4: Zumba na Caneca 2025 | J4: MB Way | K4: Banco
A5: Atuações e serenatas | B5: Entrada | C5: Sim | E5: Inscrições de tunas | F5: Inscrições e bilheteira | H5: Zumba na Caneca | J5: TPA | K5: Banco
A6: Inscrições e bilheteira | B6: Entrada | C6: Sim | E6: Bilheteira | F6: Inscrições e bilheteira | H6: 18º CITADÃO
A7: Bar e merchandising | B7: Entrada | C7: Sim | E7: Inscrições | F7: Inscrições e bilheteira | H7: 19º CITADÃO
A8: Patrocínios | B8: Entrada | C8: Sim | E8: Bar | F8: Bar e merchandising | H8: 20º CITADÃO
A9: Outros recebimentos | B9: Entrada | C9: Sim | E9: Merchandising | F9: Bar e merchandising | H9: Festivais
A10: Produção (som, luz, palco) | B10: Saída | C10: Sim | E10: Patrocínio do evento | F10: Patrocínios
A11: Alimentação e alojamento | B11: Saída | C11: Sim | E11: Outros | F11: Outros recebimentos
A12: Compras para o bar | B12: Saída | C12: Sim | E12: Som e luz | F12: Produção (som, luz, palco)
A13: Deslocações | B13: Saída | C13: Sim | E13: Palco e estruturas | F13: Produção (som, luz, palco)
A14: Prémios e troféus | B14: Saída | C14: Sim | E14: Refeições das tunas | F14: Alimentação e alojamento
A15: Instrumentos e manutenção | B15: Saída | C15: Sim | E15: Alojamento | F15: Alimentação e alojamento
A16: Merchandising e trajes | B16: Saída | C16: Sim | E16: Bebidas e consumíveis | F16: Compras para o bar
A17: Comunicação e gráfica | B17: Saída | C17: Sim | E17: Prémios | F17: Prémios e troféus
A18: Seguros e despesas bancárias | B18: Saída | C18: Sim | E18: Júri | F18: Prémios e troféus
A19: Taxas e licenças | B19: Saída | C19: Sim | E19: T-shirts | F19: Merchandising e trajes
A20: Outros pagamentos | B20: Saída | C20: Sim | E20: Cartazes e impressões | F20: Comunicação e gráfica
A21: Transferências internas | B21: Entrada e Saída | C21: Não | E21: Seguro | F21: Seguros e despesas bancárias
E22: Despesas bancárias | F22: Seguros e despesas bancárias
E23: Licenças e SPA | F23: Taxas e licenças
E24: Diversos | F24: Outros pagamentos
E25: Outros | F25: Outros pagamentos

Sheet Saldos
A1: Data | B1: Conta | C1: Saldo (€) | D1: Fonte
A2: 45291 | B2: Caixa | C2: 150 | D2: Declarado
A3: 45291 | B3: Banco | C3: 1908.6 | D3: Declarado
A4: 45657 | B4: Caixa | C4: 185.4 | D4: Contagem
A5: 45657 | B5: Banco | C5: 3912.75 | D5: Extrato
A6: 46022 | B6: Caixa | C6: 240 | D6: Contagem
A7: 46022 | B7: Banco | C7: 5991.55 | D7: Extrato
A8: 46265 | B8: Caixa | C8: 258.3 | D8: Contagem
A9: 46265 | B9: Banco | C9: 13219.75 | D9: Extrato
A10: 46295 | B10: Caixa | C10: 579 | D10: Contagem
A11: 46295 | B11: Banco | C11: 13265.05 | D11: Extrato

Sheet Movimentos
A1: Data | B1: N.º doc | C1: Descrição | D1: Atividade | E1: Rubrica | F1: Sub-rubrica | G1: Tipo | H1: Meio | I1: Valor (€) | J1: Conta (automático) | K1: Efeito no saldo (€) (automático) | L1: Conta como receita ou despesa (automático)
A2: 45332 | B2: R-001 | C2: Quotas 2024 (44 membros) | D2: Funcionamento | E2: Quotas | G2: Entrada | H2: Banco | I2: 880 | J2: =IF(H2="","",IFERROR(VLOOKUP(H2,Listas!$J$2:$K$5000,2,FALSE),"")) -> Banco | K2: =IF(OR(I2="",G2=""),"",IF(G2="Saída",-I2,I2)) -> 880 | L2: =IF(E2="","",IFERROR(VLOOKUP(E2,Listas!$A$2:$C$5000,3,FALSE),"")) -> Sim
A3: 45346 | B3: P-001 | C3: Deslocação a festival de tunas | D3: Festivais | E3: Deslocações | G3: Saída | H3: Banco | I3: 900 | J3: =IF(H3="","",IFERROR(VLOOKUP(H3,Listas!$J$2:$K$5000,2,FALSE),"")) -> Banco | K3: =IF(OR(I3="",G3=""),"",IF(G3="Saída",-I3,I3)) -> -900 | L3: =IF(E3="","",IFERROR(VLOOKUP(E3,Listas!$A$2:$C$5000,3,FALSE),"")) -> Sim
A4: 45349 | B4: P-002 | C4: Cartazes e impressões | D4: Zumba na Caneca 2024 | E4: Comunicação e gráfica | G4: Saída | H4: Banco | I4: 180 | J4: =IF(H4="","",IFERROR(VLOOKUP(H4,Listas!$J$2:$K$5000,2,FALSE),"")) -> Banco | K4: =IF(OR(I4="",G4=""),"",IF(G4="Saída",-I4,I4)) -> -180 | L4: =IF(E4="","",IFERROR(VLOOKUP(E4,Listas!$A$2:$C$5000,3,FALSE),"")) -> Sim
A5: 45353 | B5: P-003 | C5: Canecas personalizadas | D5: Zumba na Caneca 2024 | E5: Merchandising e trajes | G5: Saída | H5: Banco | I5: 300 | J5: =IF(H5="","",IFERROR(VLOOKUP(H5,Listas!$J$2:$K$5000,2,FALSE),"")) -> Banco | K5: =IF(OR(I5="",G5=""),"",IF(G5="Saída",-I5,I5)) -> -300 | L5: =IF(E5="","",IFERROR(VLOOKUP(E5,Listas!$A$2:$C$5000,3,FALSE),"")) -> Sim
A6: 45356 | B6: R-002 | C6: Patrocínio ginásio local | D6: Zumba na Caneca 2024 | E6: Patrocínios | G6: Entrada | H6: Banco | I6: 350 | J6: =IF(H6="","",IFERROR(VLOOKUP(H6,Listas!$J$2:$K$5000,2,FALSE),"")) -> Banco | K6: =IF(OR(I6="",G6=""),"",IF(G6="Saída",-I6,I6)) -> 350 | L6: =IF(E6="","",IFERROR(VLOOKUP(E6,Listas!$A$2:$C$5000,3,FALSE),"")) -> Sim
A7: 45361 | B7: P-004 | C7: Licença de ruído e SPA | D7: Zumba na Caneca 2024 | E7: Taxas e licenças | G7: Saída | H7: Caixa | I7: 100 | J7: =IF(H7="","",IFERROR(VLOOKUP(H7,Listas!$J$2:$K$5000,2,FALSE),"")) -> Caixa | K7: =IF(OR(I7="",G7=""),"",IF(G7="Saída",-I7,I7)) -> -100 | L7: =IF(E7="","",IFERROR(VLOOKUP(E7,Listas!$A$2:$C$5000,3,FALSE),"")) -> Sim
A8: 45363 | B8: R-003 | C8: Apoio anual da Câmara Municipal | D8: Funcionamento | E8: Subsídios e apoios | G8: Entrada | H8: Banco | I8: 2500 | J8: =IF(H8="","",IFERROR(VLOOKUP(H8,Listas!$J$2:$K$5000,2,FALSE),"")) -> Banco | K8: =IF(OR(I8="",G8=""),"",IF(G8="Saída",-I8,I8)) -> 2500 | L8: =IF(E8="","",IFERROR(VLOOKUP(E8,Listas!$A$2:$C$5000,3,FALSE),"")) -> Sim
A9: 45363 | B9: P-005 | C9: Aluguer de som | D9: Zumba na Caneca 2024 | E9: Produção (som, luz, palco) | G9: Saída | H9: Banco | I9: 700 | J9: =IF(H9="","",IFERROR(VLOOKUP(H9,Listas!$J$2:$K$5000,2,FALSE),"")) -> Banco | K9: =IF(OR(I9="",G9=""),"",IF(G9="Saída",-I9,I9)) -> -700 | L9: =IF(E9="","",IFERROR(VLOOKUP(E9,Listas!$A$2:$C$5000,3,FALSE),"")) -> Sim
A10: 45364 | B10: P-006 | C10: Bebidas e consumíveis | D10: Zumba na Caneca 2024 | E10: Compras para o bar | G10: Saída | H10: Banco | I10: 560 | J10: =IF(H10="","",IFERROR(VLOOKUP(H10,Listas!$J$2:$K$5000,2,FALSE),"")) -> Banco | K10: =IF(OR(I10="",G10=""),"",IF(G10="Saída",-I10,I10)) -> -560 | L10: =IF(E10="","",IFERROR(VLOOKUP(E10,Listas!$A$2:$C$5000,3,FALSE),"")) -> Sim
A11: 45367 | B11: R-004 | C11: Inscrições | D11: Zumba na Caneca 2024 | E11: Inscrições e bilheteira | G11: Entrada | H11: Caixa | I11: 1200 | J11: =IF(H11="","",IFERROR(VLOOKUP(H11,Listas!$J$2:$K$5000,2,FALSE),"")) -> Caixa | K11: =IF(OR(I11="",G11=""),"",IF(G11="Saída",-I11,I11)) -> 1200 | L11: =IF(E11="","",IFERROR(VLOOKUP(E11,Listas!$A$2:$C$5000,3,FALSE),"")) -> Sim
A12: 45367 | B12: R-005 | C12: Receita de bar | D12: Zumba na Caneca 2024 | E12: Bar e merchandising | G12: Entrada | H12: Caixa | I12: 1300 | J12: =IF(H12="","",IFERROR(VLOOKUP(H12,Listas!$J$2:$K$5000,2,FALSE),"")) -> Caixa | K12: =IF(OR(I12="",G12=""),"",IF(G12="Saída",-I12,I12)) -> 1300 | L12: =IF(E12="","",IFERROR(VLOOKUP(E12,Listas!$A$2:$C$5000,3,FALSE),"")) -> Sim
A13: 45369 | B13: T-001 | C13: Depósito do numerário do evento (saída) | D13: Zumba na Caneca 2024 | E13: Transferências internas | G13: Saída | H13: Caixa | I13: 2500 | J13: =IF(H13="","",IFERROR(VLOOKUP(H13,Listas!$J$2:$K$5000,2,FALSE),"")) -> Caixa | K13: =IF(OR(I13="",G13=""),"",IF(G13="Saída",-I13,I13)) -> -2500 | L13: =IF(E13="","",IFERROR(VLOOKUP(E13,Listas!$A$2:$C$5000,3,FALSE),"")) -> Não
... A102: 46022 | B102: P-024 | C102: Despesas bancárias de 2025 | D102: Funcionamento | E102: Seguros e despesas bancárias | G102: Saída | H102: Banco | I102: 52.4 | J102: =IF(H102="","",IFERROR(VLOOKUP(H102,Listas!$J$2:$K$5000,2,FALSE),"")) -> Banco | K102: =IF(OR(I102="",G102=""),"",IF(G102="Saída",-I102,I102)) -> -52.4 | L102: =IF(E102="","",IFERROR(VLOOKUP(E102,Listas!$A$2:$C$5000,3,FALSE),"")) -> Sim
A103: 46034 | B103: R-001 | C103: Apoio da Câmara Municipal (2.ª tranche do 19º CITADÃO) | D103: Funcionamento | E103: Subsídios e apoios | F103: Apoio CMV | G103: Entrada | H103: Banco | I103: 1000 | J103: =IF(H103="","",IFERROR(VLOOKUP(H103,Listas!$J$2:$K$5000,2,FALSE),"")) -> Banco | K103: =IF(OR(I103="",G103=""),"",IF(G103="Saída",-I103,I103)) -> 1000 | L103: =IF(E103="","",IFERROR(VLOOKUP(E103,Listas!$A$2:$C$5000,3,FALSE),"")) -> Sim
A104: 46042 | B104: P-001 | C104: Fornecedor de som: saldo do Arraial 2025 (FT 2025/311) | D104: Festivais | E104: Produção (som, luz, palco) | F104: Som e luz | G104: Saída | H104: Banco | I104: 450 | J104: =IF(H104="","",IFERROR(VLOOKUP(H104,Listas!$J$2:$K$5000,2,FALSE),"")) -> Banco | K104: =IF(OR(I104="",G104=""),"",IF(G104="Saída",-I104,I104)) -> -450 | L104: =IF(E104="","",IFERROR(VLOOKUP(E104,Listas!$A$2:$C$5000,3,FALSE),"")) -> Sim
A105: 46073 | B105: R-002 | C105: Apoio da Câmara Municipal | D105: 20º CITADÃO | E105: Subsídios e apoios | F105: Apoio CMV | G105: Entrada | H105: Banco | I105: 2500 | J105: =IF(H105="","",IFERROR(VLOOKUP(H105,Listas!$J$2:$K$5000,2,FALSE),"")) -> Banco | K105: =IF(OR(I105="",G105=""),"",IF(G105="Saída",-I105,I105)) -> 2500 | L105: =IF(E105="","",IFERROR(VLOOKUP(E105,Listas!$A$2:$C$5000,3,FALSE),"")) -> Sim
A106: 46077 | B106: P-002 | C106: Cartazes e programa | D106: 20º CITADÃO | E106: Comunicação e gráfica | G106: Saída | H106: Banco | I106: 515 | J106: =IF(H106="","",IFERROR(VLOOKUP(H106,Listas!$J$2:$K$5000,2,FALSE),"")) -> Banco | K106: =IF(OR(I106="",G106=""),"",IF(G106="Saída",-I106,I106)) -> -515 | L106: =IF(E106="","",IFERROR(VLOOKUP(E106,Listas!$A$2:$C$5000,3,FALSE),"")) -> Sim
A107: 46080 | B107: R-003 | C107: Apoio da universidade (via AE ESAV) | D107: 20º CITADÃO | E107: Subsídios e apoios | F107: Apoio UPV (via AE ESAV) | G107: Entrada | H107: Banco | I107: 1500 | J107: =IF(H107="","",IFERROR(VLOOKUP(H107,Listas!$J$2:$K$5000,2,FALSE),"")) -> Banco | K107: =IF(OR(I107="",G107=""),"",IF(G107="Saída",-I107,I107)) -> 1500 | L107: =IF(E107="","",IFERROR(VLOOKUP(E107,Listas!$A$2:$C$5000,3,FALSE),"")) -> Sim
A108: 46084 | B108: P-003 | C108: Cartazes e impressões | D108: Zumba na Caneca | E108: Comunicação e gráfica | F108: Cartazes e impressões | G108: Saída | H108: Caixa | I108: 48 | J108: =IF(H108="","",IFERROR(VLOOKUP(H108,Listas!$J$2:$K$5000,2,FALSE),"")) -> Caixa | K108: =IF(OR(I108="",G108=""),"",IF(G108="Saída",-I108,I108)) -> -48 | L108: =IF(E108="","",IFERROR(VLOOKUP(E108,Listas!$A$2:$C$5000,3,FALSE),"")) -> Sim
A109: 46086 | B109: P-004 | C109: Canecas personalizadas (300 un.) | D109: Zumba na Caneca | E109: Merchandising e trajes | G109: Saída | H109: Banco | I109: 342 | J109: =IF(H109="","",IFERROR(VLOOKUP(H109,Listas!$J$2:$K$5000,2,FALSE),"")) -> Banco | K109: =IF(OR(I109="",G109=""),"",IF(G109="Saída",-I109,I109)) -> -342 | L109: =IF(E109="","",IFERROR(VLOOKUP(E109,Listas!$A$2:$C$5000,3,FALSE),"")) -> Sim
A110: 46091 | B110: R-004 | C110: Patrocínio ginásio local | D110: Zumba na Caneca | E110: Patrocínios | F110: Patrocínio do evento | G110: Entrada | H110: Banco | I110: 150 | J110: =IF(H110="","",IFERROR(VLOOKUP(H110,Listas!$J$2:$K$5000,2,FALSE),"")) -> Banco | K110: =IF(OR(I110="",G110=""),"",IF(G110="Saída",-I110,I110)) -> 150 | L110: =IF(E110="","",IFERROR(VLOOKUP(E110,Listas!$A$2:$C$5000,3,FALSE),"")) -> Sim
A111: 46094 | B111: P-005 | C111: Bebidas e consumíveis | D111: Zumba na Caneca | E111: Compras para o bar | F111: Bebidas e consumíveis | G111: Saída | H111: Banco | I111: 612.4 | J111: =IF(H111="","",IFERROR(VLOOKUP(H111,Listas!$J$2:$K$5000,2,FALSE),"")) -> Banco | K111: =IF(OR(I111="",G111=""),"",IF(G111="Saída",-I111,I111)) -> -612.4 | L111: =IF(E111="","",IFERROR(VLOOKUP(E111,Listas!$A$2:$C$5000,3,FALSE),"")) -> Sim
A112: 46095 | B112: R-005 | C112: Inscrições (247 × 5 €) | D112: Zumba na Caneca | E112: Inscrições e bilheteira | F112: Inscrições | G112: Entrada | H112: Caixa | I112: 1235 | J112: =IF(H112="","",IFERROR(VLOOKUP(H112,Listas!$J$2:$K$5000,2,FALSE),"")) -> Caixa | K112: =IF(OR(I112="",G112=""),"",IF(G112="Saída",-I112,I112)) -> 1235 | L112: =IF(E112="","",IFERROR(VLOOKUP(E112,Listas!$A$2:$C$5000,3,FALSE),"")) -> Sim
A113: 46095 | B113: R-006 | C113: Receita de bar | D113: Zumba na Caneca | E113: Bar e merchandising | F113: Bar | G113: Entrada | H113: Caixa | I113: 1482.5 | J113: =IF(H113="","",IFERROR(VLOOKUP(H113,Listas!$J$2:$K$5000,2,FALSE),"")) -> Caixa | K113: =IF(OR(I113="",G113=""),"",IF(G113="Saída",-I113,I113)) -> 1482.5 | L113: =IF(E113="","",IFERROR(VLOOKUP(E113,Listas!$A$2:$C$5000,3,FALSE),"")) -> Sim
A114: 46095 | B114: R-007 | C114: Donativos na caixa do evento | D114: Zumba na Caneca | E114: Donativos | G114: Entrada | H114: Caixa | I114: 60 | J114: =IF(H114="","",IFERROR(VLOOKUP(H114,Listas!$J$2:$K$5000,2,FALSE),"")) -> Caixa | K114: =IF(OR(I114="",G114=""),"",IF(G114="Saída",-I114,I114)) -> 60 | L114: =IF(E114="","",IFERROR(VLOOKUP(E114,Listas!$A$2:$C$5000,3,FALSE),"")) -> Sim
A115: 46095 | B115: P-006 | C115: Instrutora de zumba | D115: Zumba na Caneca | E115: Outros pagamentos | F115: Outros | G115: Saída | H115: Caixa | I115: 200 | J115: =IF(H115="","",IFERROR(VLOOKUP(H115,Listas!$J$2:$K$5000,2,FALSE),"")) -> Caixa | K115: =IF(OR(I115="",G115=""),"",IF(G115="Saída",-I115,I115)) -> -200 | L115: =IF(E115="","",IFERROR(VLOOKUP(E115,Listas!$A$2:$C$5000,3,FALSE),"")) -> Sim
A116: 46097 | B116: P-007 | C116: Aluguer de som | D116: Zumba na Caneca | E116: Produção (som, luz, palco) | F116: Som e luz | G116: Saída | H116: Banco | I116: 180 | J116: =IF(H116="","",IFERROR(VLOOKUP(H116,Listas!$J$2:$K$5000,2,FALSE),"")) -> Banco | K116: =IF(OR(I116="",G116=""),"",IF(G116="Saída",-I116,I116)) -> -180 | L116: =IF(E116="","",IFERROR(VLOOKUP(E116,Listas!$A$2:$C$5000,3,FALSE),"")) -> Sim
A117: 46097 | B117: T-001 | C117: Depósito do numerário do evento (saída) | D117: Zumba na Caneca | E117: Transferências internas | G117: Saída | H117: Caixa | I117: 2529.5 | J117: =IF(H117="","",IFERROR(VLOOKUP(H117,Listas!$J$2:$K$5000,2,FALSE),"")) -> Caixa | K117: =IF(OR(I117="",G117=""),"",IF(G117="Saída",-I117,I117)) -> -2529.5 | L117: =IF(E117="","",IFERROR(VLOOKUP(E117,Listas!$A$2:$C$5000,3,FALSE),"")) -> Não
A118: 46097 | B118: T-001 | C118: Depósito do numerário do evento (entrada) | D118: Zumba na Caneca | E118: Transferências internas | G118: Entrada | H118: Banco | I118: 2529.5 | J118: =IF(H118="","",IFERROR(VLOOKUP(H118,Listas!$J$2:$K$5000,2,FALSE),"")) -> Banco | K118: =IF(OR(I118="",G118=""),"",IF(G118="Saída",-I118,I118)) -> 2529.5 | L118: =IF(E118="","",IFERROR(VLOOKUP(E118,Listas!$A$2:$C$5000,3,FALSE),"")) -> Não
A119: 46099 | B119: P-008 | C119: Licença de ruído e SPA | D119: Zumba na Caneca | E119: Taxas e licenças | F119: Licenças e SPA | G119: Saída | H119: Banco | I119: 65 | J119: =IF(H119="","",IFERROR(VLOOKUP(H119,Listas!$J$2:$K$5000,2,FALSE),"")) -> Banco | K119: =IF(OR(I119="",G119=""),"",IF(G119="Saída",-I119,I119)) -> -65 | L119: =IF(E119="","",IFERROR(VLOOKUP(E119,Listas!$A$2:$C$5000,3,FALSE),"")) -> Sim
A120: 46101 | B120: P-009 | C120: T-shirts do evento | D120: 20º CITADÃO | E120: Merchandising e trajes | F120: T-shirts | G120: Saída | H120: Banco | I120: 590 | J120: =IF(H120="","",IFERROR(VLOOKUP(H120,Listas!$J$2:$K$5000,2,FALSE),"")) -> Banco | K120: =IF(OR(I120="",G120=""),"",IF(G120="Saída",-I120,I120)) -> -590 | L120: =IF(E120="","",IFERROR(VLOOKUP(E120,Listas!$A$2:$C$5000,3,FALSE),"")) -> Sim
A121: 46108 | B121: P-010 | C121: Licenças e SPA | D121: 20º CITADÃO | E121: Taxas e licenças | F121: Licenças e SPA | G121: Saída | H121: Banco | I121: 310 | J121: =IF(H121="","",IFERROR(VLOOKUP(H121,Listas!$J$2:$K$5000,2,FALSE),"")) -> Banco | K121: =IF(OR(I121="",G121=""),"",IF(G121="Saída",-I121,I121)) -> -310 | L121: =IF(E121="","",IFERROR(VLOOKUP(E121,Listas!$A$2:$C$5000,3,FALSE),"")) -> Sim
A122: 46109 | B122: R-008 | C122: Inscrições das tunas | D122: 20º CITADÃO | E122: Inscrições e bilheteira | F122: Inscrições de tunas | G122: Entrada | H122: Banco | I122: 2400 | J122: =IF(H122="","",IFERROR(VLOOKUP(H122,Listas!$J$2:$K$5000,2,FALSE),"")) -> Banco | K122: =IF(OR(I122="",G122=""),"",IF(G122="Saída",-I122,I122)) -> 2400 | L122: =IF(E122="","",IFERROR(VLOOKUP(E122,Listas!$A$2:$C$5000,3,FALSE),"")) -> Sim
A123: 46113 | B123: P-011 | C123: Seguro do evento | D123: 20º CITADÃO | E123: Seguros e despesas bancárias | F123: Seguro | G123: Saída | H123: Banco | I123: 185 | J123: =IF(H123="","",IFERROR(VLOOKUP(H123,Listas!$J$2:$K$5000,2,FALSE),"")) -> Banco | K123: =IF(OR(I123="",G123=""),"",IF(G123="Saída",-I123,I123)) -> -185 | L123: =IF(E123="","",IFERROR(VLOOKUP(E123,Listas!$A$2:$C$5000,3,FALSE),"")) -> Sim
A124: 46114 | B124: R-009 | C124: Patrocínios do evento | D124: 20º CITADÃO | E124: Patrocínios | G124: Entrada | H124: Banco | I124: 2500 | J124: =IF(H124="","",IFERROR(VLOOKUP(H124,Listas!$J$2:$K$5000,2,FALSE),"")) -> Banco | K124: =IF(OR(I124="",G124=""),"",IF(G124="Saída",-I124,I124)) -> 2500 | L124: =IF(E124="","",IFERROR(VLOOKUP(E124,Listas!$A$2:$C$5000,3,FALSE),"")) -> Sim
A125: 46118 | B125: R-010 | C125: Quotas 2026 (38 membros) | D125: Funcionamento | E125: Quotas | G125: Entrada | H125: Banco | I125: 760 | J125: =IF(H125="","",IFERROR(VLOOKUP(H125,Listas!$J$2:$K$5000,2,FALSE),"")) -> Banco | K125: =IF(OR(I125="",G125=""),"",IF(G125="Saída",-I125,I125)) -> 760 | L125: =IF(E125="","",IFERROR(VLOOKUP(E125,Listas!$A$2:$C$5000,3,FALSE),"")) -> Sim
A126: 46120 | B126: P-012 | C126: Deslocação a atuação | D126: Funcionamento | E126: Deslocações | G126: Saída | H126: Banco | I126: 640 | J126: =IF(H126="","",IFERROR(VLOOKUP(H126,Listas!$J$2:$K$5000,2,FALSE),"")) -> Banco | K126: =IF(OR(I126="",G126=""),"",IF(G126="Saída",-I126,I126)) -> -640 | L126: =IF(E126="","",IFERROR(VLOOKUP(E126,Listas!$A$2:$C$5000,3,FALSE),"")) -> Sim
A127: 46122 | B127: R-011 | C127: Serenata para empresa | D127: Funcionamento | E127: Atuações e serenatas | G127: Entrada | H127: Banco | I127: 900 | J127: =IF(H127="","",IFERROR(VLOOKUP(H127,Listas!$J$2:$K$5000,2,FALSE),"")) -> Banco | K127: =IF(OR(I127="",G127=""),"",IF(G127="Saída",-I127,I127)) -> 900 | L127: =IF(E127="","",IFERROR(VLOOKUP(E127,Listas!$A$2:$C$5000,3,FALSE),"")) -> Sim
A128: 46129 | B128: P-013 | C128: Taxa de registo | D128: Funcionamento | E128: Taxas e licenças | G128: Saída | H128: Banco | I128: 40 | J128: =IF(H128="","",IFERROR(VLOOKUP(H128,Listas!$J$2:$K$5000,2,FALSE),"")) -> Banco | K128: =IF(OR(I128="",G128=""),"",IF(G128="Saída",-I128,I128)) -> -40 | L128: =IF(E128="","",IFERROR(VLOOKUP(E128,Listas!$A$2:$C$5000,3,FALSE),"")) -> Sim
A129: 46130 | B129: R-012 | C129: Quotas 2026 em numerário (17 membros) | D129: Funcionamento | E129: Quotas | G129: Entrada | H129: Caixa | I129: 340 | J129: =IF(H129="","",IFERROR(VLOOKUP(H129,Listas!$J$2:$K$5000,2,FALSE),"")) -> Caixa | K129: =IF(OR(I129="",G129=""),"",IF(G129="Saída",-I129,I129)) -> 340 | L129: =IF(E129="","",IFERROR(VLOOKUP(E129,Listas!$A$2:$C$5000,3,FALSE),"")) -> Sim
A130: 46132 | B130: R-013 | C130: Apoio da Junta de Freguesia | D130: 20º CITADÃO | E130: Subsídios e apoios | F130: Apoio Junta de Freguesia | G130: Entrada | H130: Banco | I130: 500 | J130: =IF(H130="","",IFERROR(VLOOKUP(H130,Listas!$J$2:$K$5000,2,FALSE),"")) -> Banco | K130: =IF(OR(I130="",G130=""),"",IF(G130="Saída",-I130,I130)) -> 500 | L130: =IF(E130="","",IFERROR(VLOOKUP(E130,Listas!$A$2:$C$5000,3,FALSE),"")) -> Sim
A131: 46134 | B131: P-014 | C131: Som e luz | D131: 20º CITADÃO | E131: Produção (som, luz, palco) | F131: Som e luz | G131: Saída | H131: Banco | I131: 3900 | J131: =IF(H131="","",IFERROR(VLOOKUP(H131,Listas!$J$2:$K$5000,2,FALSE),"")) -> Banco | K131: =IF(OR(I131="",G131=""),"",IF(G131="Saída",-I131,I131)) -> -3900 | L131: =IF(E131="","",IFERROR(VLOOKUP(E131,Listas!$A$2:$C$5000,3,FALSE),"")) -> Sim
A132: 46136 | B132: P-015 | C132: Palco e estruturas | D132: 20º CITADÃO | E132: Produção (som, luz, palco) | F132: Palco e estruturas | G132: Saída | H132: Banco | I132: 1150 | J132: =IF(H132="","",IFERROR(VLOOKUP(H132,Listas!$J$2:$K$5000,2,FALSE),"")) -> Banco | K132: =IF(OR(I132="",G132=""),"",IF(G132="Saída",-I132,I132)) -> -1150 | L132: =IF(E132="","",IFERROR(VLOOKUP(E132,Listas!$A$2:$C$5000,3,FALSE),"")) -> Sim
A133: 46140 | B133: P-016 | C133: Compras para o bar | D133: 20º CITADÃO | E133: Compras para o bar | G133: Saída | H133: Banco | I133: 2980.6 | J133: =IF(H133="","",IFERROR(VLOOKUP(H133,Listas!$J$2:$K$5000,2,FALSE),"")) -> Banco | K133: =IF(OR(I133="",G133=""),"",IF(G133="Saída",-I133,I133)) -> -2980.6 | L133: =IF(E133="","",IFERROR(VLOOKUP(E133,Listas!$A$2:$C$5000,3,FALSE),"")) -> Sim
A134: 46144 | B134: R-014 | C134: Bilheteira (TPA) | D134: 20º CITADÃO | E134: Inscrições e bilheteira | F134: Bilheteira | G134: Entrada | H134: TPA | I134: 3870 | J134: =IF(H134="","",IFERROR(VLOOKUP(H134,Listas!$J$2:$K$5000,2,FALSE),"")) -> Banco | K134: =IF(OR(I134="",G134=""),"",IF(G134="Saída",-I134,I134)) -> 3870 | L134: =IF(E134="","",IFERROR(VLOOKUP(E134,Listas!$A$2:$C$5000,3,FALSE),"")) -> Sim
A135: 46145 | B135: R-015 | C135: Bar (TPA) | D135: 20º CITADÃO | E135: Bar e merchandising | F135: Bar | G135: Entrada | H135: TPA | I135: 6315.2 | J135: =IF(H135="","",IFERROR(VLOOKUP(H135,Listas!$J$2:$K$5000,2,FALSE),"")) -> Banco | K135: =IF(OR(I135="",G135=""),"",IF(G135="Saída",-I135,I135)) -> 6315.2 | L135: =IF(E135="","",IFERROR(VLOOKUP(E135,Listas!$A$2:$C$5000,3,FALSE),"")) -> Sim
A136: 46145 | B136: R-016 | C136: Merchandising | D136: 20º CITADÃO | E136: Bar e merchandising | F136: Merchandising | G136: Entrada | H136: Caixa | I136: 640 | J136: =IF(H136="","",IFERROR(VLOOKUP(H136,Listas!$J$2:$K$5000,2,FALSE),"")) -> Caixa | K136: =IF(OR(I136="",G136=""),"",IF(G136="Saída",-I136,I136)) -> 640 | L136: =IF(E136="","",IFERROR(VLOOKUP(E136,Listas!$A$2:$C$5000,3,FALSE),"")) -> Sim
A137: 46146 | B137: P-017 | C137: Refeições das tunas | D137: 20º CITADÃO | E137: Alimentação e alojamento | F137: Refeições das tunas | G137: Saída | H137: Banco | I137: 3280 | J137: =IF(H137="","",IFERROR(VLOOKUP(H137,Listas!$J$2:$K$5000,2,FALSE),"")) -> Banco | K137: =IF(OR(I137="",G137=""),"",IF(G137="Saída",-I137,I137)) -> -3280 | L137: =IF(E137="","",IFERROR(VLOOKUP(E137,Listas!$A$2:$C$5000,3,FALSE),"")) -> Sim
A138: 46146 | B138: P-018 | C138: Júri | D138: 20º CITADÃO | E138: Prémios e troféus | F138: Júri | G138: Saída | H138: Caixa | I138: 420 | J138: =IF(H138="","",IFERROR(VLOOKUP(H138,Listas!$J$2:$K$5000,2,FALSE),"")) -> Caixa | K138: =IF(OR(I138="",G138=""),"",IF(G138="Saída",-I138,I138)) -> -420 | L138: =IF(E138="","",IFERROR(VLOOKUP(E138,Listas!$A$2:$C$5000,3,FALSE),"")) -> Sim
A139: 46147 | B139: P-019 | C139: Alojamento | D139: 20º CITADÃO | E139: Alimentação e alojamento | F139: Alojamento | G139: Saída | H139: Banco | I139: 1640 | J139: =IF(H139="","",IFERROR(VLOOKUP(H139,Listas!$J$2:$K$5000,2,FALSE),"")) -> Banco | K139: =IF(OR(I139="",G139=""),"",IF(G139="Saída",-I139,I139)) -> -1640 | L139: =IF(E139="","",IFERROR(VLOOKUP(E139,Listas!$A$2:$C$5000,3,FALSE),"")) -> Sim
A140: 46148 | B140: P-020 | C140: Prémios e troféus | D140: 20º CITADÃO | E140: Prémios e troféus | G140: Saída | H140: Banco | I140: 860 | J140: =IF(H140="","",IFERROR(VLOOKUP(H140,Listas!$J$2:$K$5000,2,FALSE),"")) -> Banco | K140: =IF(OR(I140="",G140=""),"",IF(G140="Saída",-I140,I140)) -> -860 | L140: =IF(E140="","",IFERROR(VLOOKUP(E140,Listas!$A$2:$C$5000,3,FALSE),"")) -> Sim
A141: 46157 | B141: P-021 | C141: Despesas bancárias de janeiro a maio | D141: Funcionamento | E141: Seguros e despesas bancárias | F141: Despesas bancárias | G141: Saída | H141: Banco | I141: 46.6 | J141: =IF(H141="","",IFERROR(VLOOKUP(H141,Listas!$J$2:$K$5000,2,FALSE),"")) -> Banco | K141: =IF(OR(I141="",G141=""),"",IF(G141="Saída",-I141,I141)) -> -46.6 | L141: =IF(E141="","",IFERROR(VLOOKUP(E141,Listas!$A$2:$C$5000,3,FALSE),"")) -> Sim
A142: 46165 | B142: R-017 | C142: Atuação em jantar de curso | D142: Funcionamento | E142: Atuações e serenatas | G142: Entrada | H142: Banco | I142: 1000 | J142: =IF(H142="","",IFERROR(VLOOKUP(H142,Listas!$J$2:$K$5000,2,FALSE),"")) -> Banco | K142: =IF(OR(I142="",G142=""),"",IF(G142="Saída",-I142,I142)) -> 1000 | L142: =IF(E142="","",IFERROR(VLOOKUP(E142,Listas!$A$2:$C$5000,3,FALSE),"")) -> Sim
A143: 46172 | B143: P-022 | C143: Gasolina e portagens | D143: Funcionamento | E143: Deslocações | G143: Saída | H143: Caixa | I143: 430 | J143: =IF(H143="","",IFERROR(VLOOKUP(H143,Listas!$J$2:$K$5000,2,FALSE),"")) -> Caixa | K143: =IF(OR(I143="",G143=""),"",IF(G143="Saída",-I143,I143)) -> -430 | L143: =IF(E143="","",IFERROR(VLOOKUP(E143,Listas!$A$2:$C$5000,3,FALSE),"")) -> Sim
A144: 46178 | B144: P-023 | C144: Deslocação a festival de tunas | D144: Festivais | E144: Deslocações | G144: Saída | H144: Banco | I144: 1210 | J144: =IF(H144="","",IFERROR(VLOOKUP(H144,Listas!$J$2:$K$5000,2,FALSE),"")) -> Banco | K144: =IF(OR(I144="",G144=""),"",IF(G144="Saída",-I144,I144)) -> -1210 | L144: =IF(E144="","",IFERROR(VLOOKUP(E144,Listas!$A$2:$C$5000,3,FALSE),"")) -> Sim
A145: 46185 | B145: P-024 | C145: Reparação de instrumentos | D145: Funcionamento | E145: Instrumentos e manutenção | G145: Saída | H145: Banco | I145: 60 | J145: =IF(H145="","",IFERROR(VLOOKUP(H145,Listas!$J$2:$K$5000,2,FALSE),"")) -> Banco | K145: =IF(OR(I145="",G145=""),"",IF(G145="Saída",-I145,I145)) -> -60 | L145: =IF(E145="","",IFERROR(VLOOKUP(E145,Listas!$A$2:$C$5000,3,FALSE),"")) -> Sim
A146: 46188 | B146: P-025 | C146: Diversos | D146: 20º CITADÃO | E146: Outros pagamentos | F146: Diversos | G146: Saída | H146: Caixa | I146: 96.4 | J146: =IF(H146="","",IFERROR(VLOOKUP(H146,Listas!$J$2:$K$5000,2,FALSE),"")) -> Caixa | K146: =IF(OR(I146="",G146=""),"",IF(G146="Saída",-I146,I146)) -> -96.4 | L146: =IF(E146="","",IFERROR(VLOOKUP(E146,Listas!$A$2:$C$5000,3,FALSE),"")) -> Sim
A147: 46193 | B147: R-018 | C147: Donativo de angariação online | D147: Funcionamento | E147: Donativos | G147: Entrada | H147: Banco | I147: 310.1 | J147: =IF(H147="","",IFERROR(VLOOKUP(H147,Listas!$J$2:$K$5000,2,FALSE),"")) -> Banco | K147: =IF(OR(I147="",G147=""),"",IF(G147="Saída",-I147,I147)) -> 310.1 | L147: =IF(E147="","",IFERROR(VLOOKUP(E147,Listas!$A$2:$C$5000,3,FALSE),"")) -> Sim
A148: 46195 | B148: P-026 | C148: Aluguer de som em festival | D148: Festivais | E148: Produção (som, luz, palco) | F148: Som e luz | G148: Saída | H148: Banco | I148: 200 | J148: =IF(H148="","",IFERROR(VLOOKUP(H148,Listas!$J$2:$K$5000,2,FALSE),"")) -> Banco | K148: =IF(OR(I148="",G148=""),"",IF(G148="Saída",-I148,I148)) -> -200 | L148: =IF(E148="","",IFERROR(VLOOKUP(E148,Listas!$A$2:$C$5000,3,FALSE),"")) -> Sim
A149: 46207 | B149: R-019 | C149: Venda de material antigo | D149: Funcionamento | E149: Outros recebimentos | G149: Entrada | H149: Caixa | I149: 79.9 | J149: =IF(H149="","",IFERROR(VLOOKUP(H149,Listas!$J$2:$K$5000,2,FALSE),"")) -> Caixa | K149: =IF(OR(I149="",G149=""),"",IF(G149="Saída",-I149,I149)) -> 79.9 | L149: =IF(E149="","",IFERROR(VLOOKUP(E149,Listas!$A$2:$C$5000,3,FALSE),"")) -> Sim
A150: 46213 | B150: P-027 | C150: Material de escritório e diversos | D150: Funcionamento | E150: Outros pagamentos | F150: Diversos | G150: Saída | H150: Caixa | I150: 95.2 | J150: =IF(H150="","",IFERROR(VLOOKUP(H150,Listas!$J$2:$K$5000,2,FALSE),"")) -> Caixa | K150: =IF(OR(I150="",G150=""),"",IF(G150="Saída",-I150,I150)) -> -95.2 | L150: =IF(E150="","",IFERROR(VLOOKUP(E150,Listas!$A$2:$C$5000,3,FALSE),"")) -> Sim
A151: 46221 | B151: R-020 | C151: Atuação em festival (cachet) | D151: Festivais | E151: Atuações e serenatas | G151: Entrada | H151: Banco | I151: 250 | J151: =IF(H151="","",IFERROR(VLOOKUP(H151,Listas!$J$2:$K$5000,2,FALSE),"")) -> Banco | K151: =IF(OR(I151="",G151=""),"",IF(G151="Saída",-I151,I151)) -> 250 | L151: =IF(E151="","",IFERROR(VLOOKUP(E151,Listas!$A$2:$C$5000,3,FALSE),"")) -> Sim
A152: 46273 | B152: R-021 | C152: Quotas recebidas (6 membros, regularização) | D152: Funcionamento | E152: Quotas | G152: Entrada | H152: Caixa | I152: 120 | J152: =IF(H152="","",IFERROR(VLOOKUP(H152,Listas!$J$2:$K$5000,2,FALSE),"")) -> Caixa | K152: =IF(OR(I152="",G152=""),"",IF(G152="Saída",-I152,I152)) -> 120 | L152: =IF(E152="","",IFERROR(VLOOKUP(E152,Listas!$A$2:$C$5000,3,FALSE),"")) -> Sim
A153: 46277 | B153: R-022 | C153: Atuação · receção ao caloiro | D153: Funcionamento | E153: Atuações e serenatas | G153: Entrada | H153: Caixa | I153: 350 | J153: =IF(H153="","",IFERROR(VLOOKUP(H153,Listas!$J$2:$K$5000,2,FALSE),"")) -> Caixa | K153: =IF(OR(I153="",G153=""),"",IF(G153="Saída",-I153,I153)) -> 350 | L153: =IF(E153="","",IFERROR(VLOOKUP(E153,Listas!$A$2:$C$5000,3,FALSE),"")) -> Sim
A154: 46280 | B154: P-028 | C154: Reparação de guitarra | D154: Funcionamento | E154: Instrumentos e manutenção | G154: Saída | H154: Caixa | I154: 85 | J154: =IF(H154="","",IFERROR(VLOOKUP(H154,Listas!$J$2:$K$5000,2,FALSE),"")) -> Caixa | K154: =IF(OR(I154="",G154=""),"",IF(G154="Saída",-I154,I154)) -> -85 | L154: =IF(E154="","",IFERROR(VLOOKUP(E154,Listas!$A$2:$C$5000,3,FALSE),"")) -> Sim
A155: 46283 | B155: R-023 | C155: Patrocinador do 20º CITADÃO (saldo) | D155: 20º CITADÃO | E155: Patrocínios | G155: Entrada | H155: Banco | I155: 250 | J155: =IF(H155="","",IFERROR(VLOOKUP(H155,Listas!$J$2:$K$5000,2,FALSE),"")) -> Banco | K155: =IF(OR(I155="",G155=""),"",IF(G155="Saída",-I155,I155)) -> 250 | L155: =IF(E155="","",IFERROR(VLOOKUP(E155,Listas!$A$2:$C$5000,3,FALSE),"")) -> Sim
A156: 46287 | B156: P-029 | C156: Renovação do seguro do equipamento | D156: Funcionamento | E156: Seguros e despesas bancárias | F156: Seguro | G156: Saída | H156: Banco | I156: 198.5 | J156: =IF(H156="","",IFERROR(VLOOKUP(H156,Listas!$J$2:$K$5000,2,FALSE),"")) -> Banco | K156: =IF(OR(I156="",G156=""),"",IF(G156="Saída",-I156,I156)) -> -198.5 | L156: =IF(E156="","",IFERROR(VLOOKUP(E156,Listas!$A$2:$C$5000,3,FALSE),"")) -> Sim
A157: 46291 | B157: P-030 | C157: Reembolso a membro (cordas, julho) | D157: Funcionamento | E157: Instrumentos e manutenção | G157: Saída | H157: Caixa | I157: 64.3 | J157: =IF(H157="","",IFERROR(VLOOKUP(H157,Listas!$J$2:$K$5000,2,FALSE),"")) -> Caixa | K157: =IF(OR(I157="",G157=""),"",IF(G157="Saída",-I157,I157)) -> -64.3 | L157: =IF(E157="","",IFERROR(VLOOKUP(E157,Listas!$A$2:$C$5000,3,FALSE),"")) -> Sim
A158: 46295 | B158: P-031 | C158: Despesas bancárias de setembro | D158: Funcionamento | E158: Seguros e despesas bancárias | F158: Despesas bancárias | G158: Saída | H158: Banco | I158: 6.2 | J158: =IF(H158="","",IFERROR(VLOOKUP(H158,Listas!$J$2:$K$5000,2,FALSE),"")) -> Banco | K158: =IF(OR(I158="",G158=""),"",IF(G158="Saída",-I158,I158)) -> -6.2 | L158: =IF(E158="","",IFERROR(VLOOKUP(E158,Listas!$A$2:$C$5000,3,FALSE),"")) -> Sim

Sheet Pendentes
A1: Tipo | B1: Entidade | C1: Descrição | D1: Atividade | E1: Valor (€) | F1: Data de registo | G1: Data de liquidação | H1: Notas
A2: A receber | B2: Câmara Municipal | C2: Apoio ao 19º CITADÃO: 2.ª tranche (Protocolo 2025) | D2: Funcionamento | E2: 1000 | F2: 45762 | G2: 46034
A3: A pagar | B3: Fornecedor de som | C3: Saldo do Arraial 2025 (fatura FT 2025/311) | D3: Festivais | E3: 450 | F3: 45894 | G3: 46042
A4: A receber | B4: Patrocinador do 20º CITADÃO | C4: Protocolo de 750 €: pagos 500 €, faltam 250 € | D4: 20º CITADÃO | E4: 250 | F4: 46114 | G4: 46283
A5: A receber | B5: Membros (6) | C5: Quotas 2026 em atraso (6 membros × 20 €) | D5: Funcionamento | E5: 120 | F5: 46173 | G5: 46273 | H5: Lista de membros em anexo
A6: A pagar | B6: Membro da tuna | C6: Reembolso de cordas compradas em julho | D6: Funcionamento | E6: 64.3 | F6: 46218 | G6: 46291 | H6: Talão anexo
A7: A receber | B7: Noivos (exemplo) | C7: Atuação em casamento de outubro: sinal por receber | D7: Funcionamento | E7: 300 | F7: 46286 | H7: Confirmado por e-mail
A8: A pagar | B8: Gráfica (exemplo) | C8: Cartazes do Arraial de outono | D8: Festivais | E8: 180 | F8: 46289 | H8: Fatura a emitir

Sheet Orçamento
A1: Âmbito | B1: Tipo | C1: Rubrica | D1: Sub-rubrica | E1: Orçado (€)
A2: 20º CITADÃO | B2: Entrada | C2: Inscrições e bilheteira | D2: Inscrições de tunas | E2: 2400
A3: 20º CITADÃO | B3: Entrada | C3: Inscrições e bilheteira | D3: Bilheteira | E3: 3500
A4: 20º CITADÃO | B4: Entrada | C4: Bar e merchandising | D4: Bar | E4: 5800
A5: 20º CITADÃO | B5: Entrada | C5: Bar e merchandising | D5: Merchandising | E5: 800
A6: 20º CITADÃO | B6: Entrada | C6: Patrocínios | E6: 3000
A7: 20º CITADÃO | B7: Entrada | C7: Subsídios e apoios | D7: Apoio CMV | E7: 2500
A8: 20º CITADÃO | B8: Entrada | C8: Subsídios e apoios | D8: Apoio UPV (via AE ESAV) | E8: 1500
A9: 20º CITADÃO | B9: Entrada | C9: Subsídios e apoios | D9: Apoio Junta de Freguesia | E9: 500
A10: 20º CITADÃO | B10: Saída | C10: Produção (som, luz, palco) | D10: Som e luz | E10: 3600
A11: 20º CITADÃO | B11: Saída | C11: Produção (som, luz, palco) | D11: Palco e estruturas | E11: 1200
A12: 20º CITADÃO | B12: Saída | C12: Alimentação e alojamento | D12: Refeições das tunas | E12: 3000
A13: 20º CITADÃO | B13: Saída | C13: Alimentação e alojamento | D13: Alojamento | E13: 1800
A14: 20º CITADÃO | B14: Saída | C14: Compras para o bar | E14: 2700
A15: 20º CITADÃO | B15: Saída | C15: Prémios e troféus | E15: 900
A16: 20º CITADÃO | B16: Saída | C16: Prémios e troféus | D16: Júri | E16: 400
A17: 20º CITADÃO | B17: Saída | C17: Comunicação e gráfica | E17: 600
A18: 20º CITADÃO | B18: Saída | C18: Taxas e licenças | D18: Licenças e SPA | E18: 300
A19: 20º CITADÃO | B19: Saída | C19: Seguros e despesas bancárias | D19: Seguro | E19: 185
A20: 20º CITADÃO | B20: Saída | C20: Merchandising e trajes | D20: T-shirts | E20: 650
A21: 20º CITADÃO | B21: Saída | C21: Outros pagamentos | D21: Diversos | E21: 200
A22: 2025 | B22: Entrada | C22: Quotas | E22: 1200
A23: 2025 | B23: Entrada | C23: Donativos | E23: 800
A24: 2025 | B24: Entrada | C24: Subsídios e apoios | E24: 4500
A25: 2025 | B25: Entrada | C25: Atuações e serenatas | E25: 3600
A26: 2025 | B26: Entrada | C26: Inscrições e bilheteira | E26: 6000
A27: 2025 | B27: Entrada | C27: Bar e merchandising | E27: 5500
A28: 2025 | B28: Entrada | C28: Patrocínios | E28: 2500
A29: 2025 | B29: Entrada | C29: Outros recebimentos | E29: 100
A30: 2025 | B30: Saída | C30: Produção (som, luz, palco) | E30: 6200
A31: 2025 | B31: Saída | C31: Alimentação e alojamento | E31: 4600
A32: 2025 | B32: Saída | C32: Compras para o bar | E32: 3000
A33: 2025 | B33: Saída | C33: Deslocações | E33: 3000
... A40: 2025 | B40: Saída | C40: Outros pagamentos | E40: 150

Sheet Géneros
A1: Data | B1: Atividade | C1: Tipo | D1: Quantidade | E1: Em falta | F1: Valor estimado (€)
A2: 46142 | B2: 20º CITADÃO | C2: UPV: cedência da Aula Magna, CAFAC e Pala do CAFAC | D2: 4 dias | F2: 2400
A3: 46142 | B3: 20º CITADÃO | C3: CMV: transporte das tunas (autocarro municipal) | D3: 2 viagens | F3: 380
A4: 46142 | B4: 20º CITADÃO | C4: Ginásio parceiro: cadeiras e mesas | D4: 150 un. | F4: 150

Sheet CITADÃO 2026
A1: Relatório | B1: Relatório de evento
A2: Versão do modelo | B2: 1
A4: Atividade | B4: 20º CITADÃO
A5: Início do evento | B5: 46142 | C5: Opcional. Se só um dos dois estiver preenchido, o evento é de um dia.
A6: Fim do evento | B6: 46145
A7: Contar movimentos até | B7: 46188 | C7: Opcional. Os movimentos depois desta data não entram.
A8: Pendentes à data de | C8: Em branco: a data de "Contar movimentos até" ou a do último movimento.
A9: Orçamento a usar | C9: Em branco: o orçamento com o nome da atividade.
A11: Indicadores
A12: Indicador | B12: Valor
A13: Bilhetes vendidos | B13: 645
A14: Tunas participantes | B14: 8
A15: Custo de acolhimento por tuna (refeições + alojamento) | B15: 615,00 €
A16: Margem do bar (receita − compras) | B16: 3.334,60 €
A17: Peso dos apoios públicos no recebido | B17: 22,2%
A22: Notas | C22: Um parágrafo por linha.
A23: Bilheteira e bar acima do orçado; patrocínios abaixo por falta de um protocolo. Para o próximo CITADÃO: fechar patrocínios até fevereiro e orçar alimentação com o preço por refeição já negociado.
A29: Assinaturas | C29: Escreva o nome ao lado de cada cargo.
A30: Cargo | B30: Nome
A31: Coordenação do evento
A32: Tesoureiro(a)

Sheet Zumba 2026
A1: Relatório | B1: Relatório de evento
A2: Versão do modelo | B2: 1
A4: Atividade | B4: Zumba na Caneca
A5: Início do evento | B5: 46095 | C5: Opcional. Se só um dos dois estiver preenchido, o evento é de um dia.
A6: Fim do evento | B6: 46095
A7: Contar movimentos até | C7: Opcional. Os movimentos depois desta data não entram.
A8: Pendentes à data de | B8: 46099 | C8: Em branco: a data de "Contar movimentos até" ou a do último movimento.
A9: Orçamento a usar | C9: Em branco: o orçamento com o nome da atividade.
A11: Indicadores
A12: Indicador | B12: Valor
A13: Inscrições | B13: 247
A14: Por participante | B14: 5,99 €
A22: Notas | C22: Um parágrafo por linha.
A23: O resultado do evento reverte para o 20º CITADÃO. O numerário do evento (2.777,50 € recebidos, 248,00 € pagos em mão) foi depositado no banco a 16/03/2026.
A29: Assinaturas | C29: Escreva o nome ao lado de cada cargo.
A30: Cargo | B30: Nome
A31: Coordenação do evento
A32: Tesoureiro(a)

Sheet Pegada 2026
A1: Relatório | B1: Pegada de direção
A2: Versão do modelo | B2: 1
A4: Data do último relatório | C4: Em branco: o fim do relatório anterior deste ficheiro.
A5: Data da passagem | B5: 46295
A6: Direção cessante | B6: Direção 2025/26
A7: Direção entrante | B7: Direção 2026/27
A8: Saldo do extrato bancário na data da passagem (€) | B8: 13265.05
A9: Moedas não contadas uma a uma (valor total, €) | B9: 6 | C9: Moedas guardadas em saco ou rolo, sem contar uma a uma.
A11: Pagamentos emitidos ainda não debitados no extrato | C11: Cheques ou transferências feitos que o banco ainda não mostra.
A12: Descrição | B12: Valor (€)
A19: Depósitos ainda não creditados no extrato | C19: Depósitos feitos que o banco ainda não mostra.
A20: Descrição | B20: Valor (€)
A27: Contagem de caixa
A28: Denominação (€) | B28: Quantidade | C28: Total (€)
A29: 500 | C29: =A29*B29 -> 0
A30: 200 | C30: =A30*B30 -> 0
A31: 100 | C31: =A31*B31 -> 0
A32: 50 | B32: 8 | C32: =A32*B32 -> 400
A33: 20 | B33: 5 | C33: =A33*B33 -> 100
A34: 10 | B34: 3 | C34: =A34*B34 -> 30
A35: 5 | B35: 5 | C35: =A35*B35 -> 25
A36: 2 | B36: 6 | C36: =A36*B36 -> 12
A37: 1 | B37: 6 | C37: =A37*B37 -> 6
A38: 0.5 | C38: =A38*B38 -> 0
A39: 0.2 | C39: =A39*B39 -> 0
A40: 0.1 | C40: =A40*B40 -> 0
A41: 0.05 | C41: =A41*B41 -> 0
A42: 0.02 | C42: =A42*B42 -> 0
A43: 0.01 | C43: =A43*B43 -> 0
A45: Notas | C45: Um parágrafo por linha.
A46: Valores, pendentes e acessos conferidos pelas duas direções e pelo Conselho Fiscal.
A52: Assinaturas | C52: Escreva o nome ao lado de cada cargo.
A53: Cargo | B53: Nome
A54: Direção cessante
A55: Direção entrante
A56: Conselho Fiscal

Sheet Letivo 2025-26
A1: Relatório | B1: Fim de ano letivo
A2: Versão do modelo | B2: 1
A4: Início do período | C4: Em branco: o dia seguinte ao fim do relatório anterior deste ficheiro.
A5: Fim do período | B5: 46265
A6: Orçamento a usar | C6: Em branco: o relatório não tem secção de orçamento.
A7: Incluir a lista de movimentos | B7: Sim | C7: Em branco: Sim.
A9: Notas | C9: Um parágrafo por linha.
A10: Ano letivo marcado pelo 20º CITADÃO e pela Zumba na Caneca. As quotas em atraso foram regularizadas em setembro.
A16: Assinaturas | C16: Escreva o nome ao lado de cada cargo.
A17: Cargo | B17: Nome
A18: Tesoureiro(a)
A19: Presidente da Direção

Sheet Fiscal 2025
A1: Relatório | B1: Fim de ano fiscal
A2: Versão do modelo | B2: 1
A4: Ano | B4: 2025
A5: Orçamento a usar | B5: 2025 | C5: Em branco: o orçamento com o nome do ano.
A6: Incluir a lista de movimentos | B6: Não | C6: Em branco: Não.
A8: Parecer do Conselho Fiscal
A9: O Conselho Fiscal verificou os mapas, os extratos bancários e os documentos de suporte e emite parecer favorável à aprovação das contas de 2025.
A15: Notas | C15: Um parágrafo por linha.
A16: Resultado de caixa positivo, com o saldo bancário conferido com o extrato de 31/12/2025.
A22: Assinaturas | C22: Escreva o nome ao lado de cada cargo.
A23: Cargo | B23: Nome
A24: Presidente da Direção
A25: Tesoureiro(a)
A26: Presidente do Conselho Fiscal
