Workbook

Sheet Instruções
A1: Modelo de tesouraria do TUNADÃO 1998
A2: Este ficheiro reúne os dados da tesouraria. Depois de preenchido, carregue-o na página do gerador de relatórios para obter o relatório em PDF.
A3: Todas as linhas de exemplo são fictícias. Apague-as antes de começar a registar os seus movimentos.
A5: Para que serve cada separador
A6: Movimentos: cada recebimento e cada pagamento, com a data em que o dinheiro entrou ou saiu. A tuna trabalha em regime de caixa, por isso só contam os movimentos de dinheiro.
A7: Pendentes: valores a receber e dívidas a pagar que ainda não foram liquidados. Preencha a data de liquidação quando o dinheiro mudar de mãos e registe então o movimento correspondente.
A8: Orçamento: o valor orçado por rubrica, para uma atividade ou para um período (por exemplo, "20º CITADÃO" ou "2026").
A9: Géneros: apoios em espécie. São listados à parte e nunca entram no saldo.
A10: Saldos: pontos de controlo do dinheiro que existe em cada conta. Ver a secção seguinte.
A11: Listas: as rubricas, sub-rubricas, atividades e meios de pagamento que aparecem nas listas suspensas dos outros separadores.
A13: Como funcionam os pontos de controlo (Saldos)
A14: Cada linha indica o saldo de uma conta (Caixa ou Banco) no fim de um dia, depois de contar todos os movimentos desse dia: é o saldo contabilístico, não o saldo disponível.
... A29: Para acrescentar uma rubrica, atividade ou meio, escreva-o no fim da respetiva coluna do separador Listas. As listas suspensas passam a incluí-lo.

Sheet Movimentos
A1: Data | B1: N.º doc | C1: Descrição | D1: Atividade | E1: Rubrica | F1: Sub-rubrica | G1: Tipo | H1: Meio | I1: Valor (€) | J1: Conta | K1: Valor com sinal (€) | L1: Conta para o resultado
A2: 46058 | B2: R-001 | C2: Inscrições (exemplo fictício) | D2: Zumba na Caneca | E2: Inscrições e bilheteira | F2: Bilheteira | G2: Entrada | H2: Caixa | I2: 120 | J2: =IF(H2="","",IFERROR(VLOOKUP(H2,Listas!$J$2:$K$1048576,2,FALSE),"")) -> Caixa | K2: =IF(OR(I2="",G2=""),"",IF(G2="Saída",-I2,I2)) -> 120 | L2: =IF(E2="","",IFERROR(VLOOKUP(E2,Listas!$A$2:$C$1048576,3,FALSE),"")) -> Sim
A3: 46059 | B3: P-001 | C3: Cartazes e impressões (exemplo fictício) | D3: Zumba na Caneca | E3: Comunicação e gráfica | F3: Cartazes e impressões | G3: Saída | H3: Caixa | I3: 48 | J3: =IF(H3="","",IFERROR(VLOOKUP(H3,Listas!$J$2:$K$1048576,2,FALSE),"")) -> Caixa | K3: =IF(OR(I3="",G3=""),"",IF(G3="Saída",-I3,I3)) -> -48 | L3: =IF(E3="","",IFERROR(VLOOKUP(E3,Listas!$A$2:$C$1048576,3,FALSE),"")) -> Sim
A4: 46063 | B4: P-002 | C4: Aluguer de som (exemplo fictício) | D4: Zumba na Caneca | E4: Produção (som, luz, palco) | F4: Som e luz | G4: Saída | H4: Banco | I4: 300 | J4: =IF(H4="","",IFERROR(VLOOKUP(H4,Listas!$J$2:$K$1048576,2,FALSE),"")) -> Banco | K4: =IF(OR(I4="",G4=""),"",IF(G4="Saída",-I4,I4)) -> -300 | L4: =IF(E4="","",IFERROR(VLOOKUP(E4,Listas!$A$2:$C$1048576,3,FALSE),"")) -> Sim
A5: 46065 | B5: R-002 | C5: Patrocínio do ginásio (exemplo fictício) | D5: Zumba na Caneca | E5: Patrocínios | F5: Patrocínio do evento | G5: Entrada | H5: Banco | I5: 500 | J5: =IF(H5="","",IFERROR(VLOOKUP(H5,Listas!$J$2:$K$1048576,2,FALSE),"")) -> Banco | K5: =IF(OR(I5="",G5=""),"",IF(G5="Saída",-I5,I5)) -> 500 | L5: =IF(E5="","",IFERROR(VLOOKUP(E5,Listas!$A$2:$C$1048576,3,FALSE),"")) -> Sim
A6: 46068 | C6: Vendas do bar por TPA (exemplo fictício) | D6: Zumba na Caneca | E6: Bar e merchandising | F6: Bar | G6: Entrada | H6: TPA | I6: 85.5 | J6: =IF(H6="","",IFERROR(VLOOKUP(H6,Listas!$J$2:$K$1048576,2,FALSE),"")) -> Banco | K6: =IF(OR(I6="",G6=""),"",IF(G6="Saída",-I6,I6)) -> 85.5 | L6: =IF(E6="","",IFERROR(VLOOKUP(E6,Listas!$A$2:$C$1048576,3,FALSE),"")) -> Sim
A7: 46069 | B7: P-003 | C7: Caução do alojamento (exemplo fictício) | D7: 20º CITADÃO | E7: Alimentação e alojamento | F7: Alojamento | G7: Saída | H7: Banco | I7: 400 | J7: =IF(H7="","",IFERROR(VLOOKUP(H7,Listas!$J$2:$K$1048576,2,FALSE),"")) -> Banco | K7: =IF(OR(I7="",G7=""),"",IF(G7="Saída",-I7,I7)) -> -400 | L7: =IF(E7="","",IFERROR(VLOOKUP(E7,Listas!$A$2:$C$1048576,3,FALSE),"")) -> Sim
A8: 46073 | B8: R-003 | C8: Devolução de parte da caução (exemplo de reembolso) | D8: 20º CITADÃO | E8: Alimentação e alojamento | F8: Alojamento | G8: Entrada | H8: Banco | I8: 100 | J8: =IF(H8="","",IFERROR(VLOOKUP(H8,Listas!$J$2:$K$1048576,2,FALSE),"")) -> Banco | K8: =IF(OR(I8="",G8=""),"",IF(G8="Saída",-I8,I8)) -> 100 | L8: =IF(E8="","",IFERROR(VLOOKUP(E8,Listas!$A$2:$C$1048576,3,FALSE),"")) -> Sim
A9: 46075 | B9: T-001 | C9: Depósito de numerário (saída da caixa) | D9: Funcionamento | E9: Transferências internas | G9: Saída | H9: Caixa | I9: 100 | J9: =IF(H9="","",IFERROR(VLOOKUP(H9,Listas!$J$2:$K$1048576,2,FALSE),"")) -> Caixa | K9: =IF(OR(I9="",G9=""),"",IF(G9="Saída",-I9,I9)) -> -100 | L9: =IF(E9="","",IFERROR(VLOOKUP(E9,Listas!$A$2:$C$1048576,3,FALSE),"")) -> Não
A10: 46075 | B10: T-001 | C10: Depósito de numerário (entrada no banco) | D10: Funcionamento | E10: Transferências internas | G10: Entrada | H10: Banco | I10: 100 | J10: =IF(H10="","",IFERROR(VLOOKUP(H10,Listas!$J$2:$K$1048576,2,FALSE),"")) -> Banco | K10: =IF(OR(I10="",G10=""),"",IF(G10="Saída",-I10,I10)) -> 100 | L10: =IF(E10="","",IFERROR(VLOOKUP(E10,Listas!$A$2:$C$1048576,3,FALSE),"")) -> Não
J11: =IF(H11="","",IFERROR(VLOOKUP(H11,Listas!$J$2:$K$1048576,2,FALSE),"")) | K11: =IF(OR(I11="",G11=""),"",IF(G11="Saída",-I11,I11)) | L11: =IF(E11="","",IFERROR(VLOOKUP(E11,Listas!$A$2:$C$1048576,3,FALSE),""))
J12: =IF(H12="","",IFERROR(VLOOKUP(H12,Listas!$J$2:$K$1048576,2,FALSE),"")) | K12: =IF(OR(I12="",G12=""),"",IF(G12="Saída",-I12,I12)) | L12: =IF(E12="","",IFERROR(VLOOKUP(E12,Listas!$A$2:$C$1048576,3,FALSE),""))
J13: =IF(H13="","",IFERROR(VLOOKUP(H13,Listas!$J$2:$K$1048576,2,FALSE),"")) | K13: =IF(OR(I13="",G13=""),"",IF(G13="Saída",-I13,I13)) | L13: =IF(E13="","",IFERROR(VLOOKUP(E13,Listas!$A$2:$C$1048576,3,FALSE),""))
J14: =IF(H14="","",IFERROR(VLOOKUP(H14,Listas!$J$2:$K$1048576,2,FALSE),"")) | K14: =IF(OR(I14="",G14=""),"",IF(G14="Saída",-I14,I14)) | L14: =IF(E14="","",IFERROR(VLOOKUP(E14,Listas!$A$2:$C$1048576,3,FALSE),""))
J15: =IF(H15="","",IFERROR(VLOOKUP(H15,Listas!$J$2:$K$1048576,2,FALSE),"")) | K15: =IF(OR(I15="",G15=""),"",IF(G15="Saída",-I15,I15)) | L15: =IF(E15="","",IFERROR(VLOOKUP(E15,Listas!$A$2:$C$1048576,3,FALSE),""))
J16: =IF(H16="","",IFERROR(VLOOKUP(H16,Listas!$J$2:$K$1048576,2,FALSE),"")) | K16: =IF(OR(I16="",G16=""),"",IF(G16="Saída",-I16,I16)) | L16: =IF(E16="","",IFERROR(VLOOKUP(E16,Listas!$A$2:$C$1048576,3,FALSE),""))
J17: =IF(H17="","",IFERROR(VLOOKUP(H17,Listas!$J$2:$K$1048576,2,FALSE),"")) | K17: =IF(OR(I17="",G17=""),"",IF(G17="Saída",-I17,I17)) | L17: =IF(E17="","",IFERROR(VLOOKUP(E17,Listas!$A$2:$C$1048576,3,FALSE),""))
J18: =IF(H18="","",IFERROR(VLOOKUP(H18,Listas!$J$2:$K$1048576,2,FALSE),"")) | K18: =IF(OR(I18="",G18=""),"",IF(G18="Saída",-I18,I18)) | L18: =IF(E18="","",IFERROR(VLOOKUP(E18,Listas!$A$2:$C$1048576,3,FALSE),""))
J19: =IF(H19="","",IFERROR(VLOOKUP(H19,Listas!$J$2:$K$1048576,2,FALSE),"")) | K19: =IF(OR(I19="",G19=""),"",IF(G19="Saída",-I19,I19)) | L19: =IF(E19="","",IFERROR(VLOOKUP(E19,Listas!$A$2:$C$1048576,3,FALSE),""))
J20: =IF(H20="","",IFERROR(VLOOKUP(H20,Listas!$J$2:$K$1048576,2,FALSE),"")) | K20: =IF(OR(I20="",G20=""),"",IF(G20="Saída",-I20,I20)) | L20: =IF(E20="","",IFERROR(VLOOKUP(E20,Listas!$A$2:$C$1048576,3,FALSE),""))
J21: =IF(H21="","",IFERROR(VLOOKUP(H21,Listas!$J$2:$K$1048576,2,FALSE),"")) | K21: =IF(OR(I21="",G21=""),"",IF(G21="Saída",-I21,I21)) | L21: =IF(E21="","",IFERROR(VLOOKUP(E21,Listas!$A$2:$C$1048576,3,FALSE),""))
J22: =IF(H22="","",IFERROR(VLOOKUP(H22,Listas!$J$2:$K$1048576,2,FALSE),"")) | K22: =IF(OR(I22="",G22=""),"",IF(G22="Saída",-I22,I22)) | L22: =IF(E22="","",IFERROR(VLOOKUP(E22,Listas!$A$2:$C$1048576,3,FALSE),""))
... J5000: =IF(H5000="","",IFERROR(VLOOKUP(H5000,Listas!$J$2:$K$1048576,2,FALSE),"")) | K5000: =IF(OR(I5000="",G5000=""),"",IF(G5000="Saída",-I5000,I5000)) | L5000: =IF(E5000="","",IFERROR(VLOOKUP(E5000,Listas!$A$2:$C$1048576,3,FALSE),""))

Sheet Pendentes
A1: Tipo | B1: Entidade | C1: Descrição | D1: Atividade | E1: Valor (€) | F1: Data de registo | G1: Data de liquidação | H1: Notas
A2: A receber | B2: Câmara Municipal (exemplo) | C2: Apoio ao evento por receber | D2: Zumba na Caneca | E2: 250 | F2: 46063 | H2: Protocolo assinado, pagamento previsto em março
A3: A pagar | B3: Gráfica Exemplo | C3: Impressão de t-shirts | D3: Festivais | E3: 180 | F3: 46073

Sheet Orçamento
A1: Âmbito | B1: Tipo | C1: Rubrica | D1: Sub-rubrica | E1: Orçado (€)
A2: Zumba na Caneca | B2: Entrada | C2: Inscrições e bilheteira | D2: Bilheteira | E2: 400
A3: Zumba na Caneca | B3: Saída | C3: Produção (som, luz, palco) | D3: Som e luz | E3: 300
A4: 2026 | B4: Saída | C4: Comunicação e gráfica | E4: 200

Sheet Géneros
A1: Data | B1: Atividade | C1: Tipo | D1: Quantidade | E1: Em falta | F1: Valor estimado (€)
A2: 46067 | B2: Zumba na Caneca | C2: Cedência de sala (exemplo) | D2: 1 dia | F2: 150
B3: Festivais | C3: Cartazes oferecidos (exemplo) | D3: 20 unidades | E3: 5

Sheet Saldos
A1: Data | B1: Conta | C1: Saldo (€) | D1: Fonte
A2: 46053 | B2: Caixa | C2: 150 | D2: Contagem
A3: 46053 | B3: Banco | C3: 3000 | D3: Extrato
A4: 46081 | B4: Caixa | C4: 122 | D4: Contagem
A5: 46081 | B5: Banco | C5: 3085.5 | D5: Extrato

Sheet Listas
A1: Rubrica | B1: Tipo | C1: Conta para o resultado | E1: Sub-rubrica | F1: Rubrica | H1: Atividade | J1: Meio | K1: Conta
A2: Quotas | B2: Entrada | C2: Sim | E2: Apoio CMV | F2: Subsídios e apoios | H2: Funcionamento | J2: Caixa | K2: Caixa
A3: Donativos | B3: Entrada | C3: Sim | E3: Apoio UPV (via AE ESAV) | F3: Subsídios e apoios | H3: Zumba na Caneca | J3: Banco | K3: Banco
A4: Subsídios e apoios | B4: Entrada | C4: Sim | E4: Apoio Junta de Freguesia | F4: Subsídios e apoios | H4: 20º CITADÃO | J4: MB Way | K4: Banco
A5: Atuações e serenatas | B5: Entrada | C5: Sim | E5: Inscrições de tunas | F5: Inscrições e bilheteira | H5: Festivais | J5: TPA | K5: Banco
A6: Inscrições e bilheteira | B6: Entrada | C6: Sim | E6: Bilheteira | F6: Inscrições e bilheteira
A7: Bar e merchandising | B7: Entrada | C7: Sim | E7: Inscrições | F7: Inscrições e bilheteira
A8: Patrocínios | B8: Entrada | C8: Sim | E8: Bar | F8: Bar e merchandising
A9: Outros recebimentos | B9: Entrada | C9: Sim | E9: Merchandising | F9: Bar e merchandising
A10: Produção (som, luz, palco) | B10: Saída | C10: Sim | E10: Patrocínio do evento | F10: Patrocínios
A11: Alimentação e alojamento | B11: Saída | C11: Sim | E11: Outros | F11: Outros recebimentos
A12: Compras para o bar | B12: Saída | C12: Sim | E12: Som e luz | F12: Produção (som, luz, palco)
A13: Deslocações | B13: Saída | C13: Sim | E13: Palco e estruturas | F13: Produção (som, luz, palco)
A14: Prémios e troféus | B14: Saída | C14: Sim | E14: Refeições das tunas | F14: Alimentação e alojamento
A15: Instrumentos e manutenção | B15: Saída | C15: Sim | E15: Alojamento | F15: Alimentação e alojamento
A16: Merchandising e trajes | B16: Saída | C16: Sim | E16: Bebidas e consumíveis | F16: Compras para o bar
A17: Comunicação e gráfica | B17: Saída | C17: Sim | E17: Prémios | F17: Prémios e troféus
... A20: Outros pagamentos | B20: Saída | C20: Sim | E20: Cartazes e impressões | F20: Comunicação e gráfica
A21: Transferências internas | C21: Não | E21: Seguro | F21: Seguros e despesas bancárias
E22: Despesas bancárias | F22: Seguros e despesas bancárias
E23: Licenças e SPA | F23: Taxas e licenças
E24: Diversos | F24: Outros pagamentos
E25: Outros | F25: Outros pagamentos
